setup.py
distributions_pk/Binomialdistribution.py
distributions_pk/Gaussiandistribution.py
distributions_pk/Generaldistribution.py
distributions_pk/__init__.py
distributions_pk.egg-info/PKG-INFO
distributions_pk.egg-info/SOURCES.txt
distributions_pk.egg-info/dependency_links.txt
distributions_pk.egg-info/not-zip-safe
distributions_pk.egg-info/top_level.txt