Metadata-Version: 1.0
Name: distributions-pk
Version: 0.2
Summary: Gaussian distributions
Home-page: UNKNOWN
Author: Prabhat Kedia
Author-email: prabhatkedia07@gmail.com
License: UNKNOWN
Platform: UNKNOWN
